mubofo/__init__.py
mubofo/_forests.py
mubofo/_trees.py
mubofo/py.typed
mubofo-0.2.8.dist-info/LICENSE
mubofo-0.2.8.dist-info/WHEEL
mubofo-0.2.8.dist-info/METADATA
mubofo-0.2.8.dist-info/RECORD
