Metadata-Version: 2.1
Name: mubofo
Version: 0.2.8
Summary: Boosted forest regression with native support for multioutput problems.
Author-email: Dave Connelly <dsconnelly@nyu.edu>
Requires-Dist: numpy
Requires-Dist: scikit-learn
Project-URL: Home, https://github.com/dsconnelly/mubofo
